{
    "dataPerson": [
      {
        "id": 1,
        "name": "John Doe",
        "gender": "Male",
        "age": 28,
        "address": "1234 Elm Street, Springfield, IL"
      },
      {
        "id": 2,
        "name": "Jane Smith",
        "gender": "Female",
        "age": 34,
        "address": "5678 Oak Avenue, Rivertown, TX"
      },
      {
        "id": 3,
        "name": "Alice Johnson",
        "gender": "Female",
        "age": 25,
        "address": "9101 Pine Road, Lakeside, CA"
      },
      {
        "id": 4,
        "name": "Bob Brown",
        "gender": "Male",
        "age": 42,
        "address": "1122 Maple Drive, Greenfield, OH"
      },
      {
        "id": 5,
        "name": "Charlie Davis",
        "gender": "Male",
        "age": 19,
        "address": "3344 Birch Boulevard, Clearwater, FL"
      }
    ]
  }
  